<odoo>
    <data>
        <record id="jc_group_sale_self" model="res.groups">
            <field name="name">业务员</field>
            <field name="category_id" ref="archives.jc_sale"/>
            <field name="implied_ids" eval="[(4, ref('base.group_user'))]"/>
            <field name="comment">用户只能访问自己做的销售单据.</field>
        </record>

        <record id="jc_group_sale_all" model="res.groups">
            <field name="name">经理</field>
            <field name="category_id" ref="archives.jc_sale"/>
            <field name="implied_ids" eval="[(4, ref('jc_group_sale_self'))]"/>
            <field name="comment">用户可以访问所有人做的销售单据.</field>
        </record>

        <record id="jc_rule_sale_order_all" model="ir.rule">
            <field name="name">全部销售订单</field>
            <field ref="model_jc_sale_sale_order" name="model_id"/>
            <field name="domain_force">[(1,'=',1)]</field>
            <field name="groups" eval="[(4, ref('jc_sale.jc_group_sale_all'))]"/>
        </record>

        <record id="jc_rule_sale_order_self" model="ir.rule">
            <field name="name">私人销售订单</field>
            <field ref="model_jc_sale_sale_order" name="model_id"/>
            <field name="domain_force">['|',('create_uid','=',user.id),('create_uid','=',False)]</field>
            <field name="groups" eval="[(4, ref('jc_sale.jc_group_sale_self'))]"/>
        </record>

        <record id="jc_rule_sale_forecast_all" model="ir.rule">
            <field name="name">全部销售预报</field>
            <field ref="model_jc_sale_sale_forecast" name="model_id"/>
            <field name="domain_force">[(1,'=',1)]</field>
            <field name="groups" eval="[(4, ref('jc_sale.jc_group_sale_all'))]"/>
        </record>

        <record id="jc_rule_sale_forecast_self" model="ir.rule">
            <field name="name">私人销售预报</field>
            <field ref="model_jc_sale_sale_forecast" name="model_id"/>
            <field name="domain_force">['|',('create_uid','=',user.id),('create_uid','=',False)]</field>
            <field name="groups" eval="[(4, ref('jc_sale.jc_group_sale_self'))]"/>
        </record>

        <record id="jc_group_sale_price_see" model="res.groups">
            <field name="name">查看销售价格</field>
            <field name="category_id" ref="archives.jc_price"/>
            <!--<field name="implied_ids" eval="[(4, ref('base.group_user'))]"/>-->
            <field name="comment">用户能在销售单据中看到价格.</field>
        </record>

        <record id="jc_group_sale_price_manager" model="res.groups">
            <field name="name">管理销售价格</field>
            <field name="category_id" ref="archives.jc_price"/>
            <!--<field name="implied_ids" eval="[(4, ref('base.group_user'))]"/>-->
            <field name="comment">用户能为销售单据设置价格单.</field>
        </record>

    </data>
</odoo>